camt_to_erpnext/__init__.py
camt_to_erpnext/__main__.py
camt_to_erpnext/main.py
camt_to_erpnext-0.2.2.dist-info/entry_points.txt
camt_to_erpnext-0.2.2.dist-info/LICENSE
camt_to_erpnext-0.2.2.dist-info/WHEEL
camt_to_erpnext-0.2.2.dist-info/METADATA
camt_to_erpnext-0.2.2.dist-info/RECORD
