Metadata-Version: 2.1
Name: camt-to-erpnext
Version: 0.2.2
Summary: Convert a CAMT CSV file into a normal CSV file that can be used for importing Bank Transactions into ERPNext.
Home-page: https://github.com/barredterra/camt-to-erpnext
Author: barredterra
Author-email: 14891507+barredterra@users.noreply.github.com
Requires-Python: >=3.10,<4.0
Classifier: Intended Audience :: End Users/Desktop
Classifier: License :: OSI Approved :: MIT License
Classifier: Natural Language :: German
Classifier: Programming Language :: Python :: 3
Classifier: Programming Language :: Python :: 3.10
Classifier: Topic :: Office/Business :: Financial :: Accounting
Requires-Dist: typer[all] (>=0.6.1,<0.7.0)
Project-URL: Repository, https://github.com/barredterra/camt-to-erpnext
